[
    {
        "name": "Joneten",
        "job": "Chairman",
        "imageUrl": "/images/teams/Joneten.jpeg",
        "links": {
            "instagram": "https://www.instagram.com/jonetensaputra/"
        }
    },
    {
        "name": "Sofian Hadiwijaya",
        "job": "Advisor / Patron",
        "imageUrl": "/images/teams/Sofian.jpeg",
        "links": {
            "github": "https://github.com/sofianhw",
            "linkedin": "https://www.linkedin.com/in/sofianhw",
            "instagram": "https://www.instagram.com/sofianhw"
        }
    },
    {
        "name": "Arief Rahmansyah",
        "job": "Engineering Manager",
        "imageUrl": "/images/teams/Arief.jpg",
        "links": {
            "github": "https://github.com/ariefrahmansyah",
            "instagram": "https://www.instagram.com/ariefrahmansyah/"
        }
    },
    {
        "name": "Faisal Morensya",
        "job": "Engineering Manager",
        "imageUrl": "/images/teams/Faisal.jpeg",
        "links": {
            "github": "https://github.com/lloistborn",
            "instagram": "https://www.instagram.com/morensya/"
        }
    },
    {
        "name": "Novita Hidayati",
        "job": "Product Manager",
        "imageUrl": "/images/teams/Novita.jpg",
        "links": {
            "github": "https://github.com/hinovita",
            "linkedin": "www.linkedin.com/in/hinovita",
            "instagram": "https://www.instagram.com/hi_novita/",
            "dribbble": "https://dribbble.com/hinovita"
        }
    },
    {
        "name": "Roylisto Putra Pradana",
        "job": "Facilitator",
        "imageUrl": "/images/teams/Roylisto.jpeg",
        "links": {
            "github": "https://github.com/tokanggit",
            "linkedin": "https://www.linkedin.com/in/roylisto/",
            "instagram": "https://www.instagram.com/roylisto/"
        }
    },
    {
        "name": "Salahudin Al Ayubi",
        "job": "UI/UX Lead",
        "imageUrl": "/images/teams/Salahudin.jpg",
        "links": {
            "github": "https://github.com/salahudinalyb",
            "linkedin": "https://www.linkedin.com/in/salahudin-al-ayubi04/",
            "instagram": "https://www.instagram.com/salyubi/",
            "dribbble": "https://dribbble.com/salyubi"
        }
    },
    {
        "name": "Annisa Isma Abella",
        "job": "Event Management Lead",
        "imageUrl": "/images/teams/Annisa.jpg",
        "links": {
            "github": "https://github.com/annisaaismaa",
            "linkedin": "https://www.linkedin.com/in/annisaaismaa",
            "instagram": "https://www.instagram.com/annisaaismaa/"
        }
    },
    {
        "name": "Ahmad Emir Alfatah",
        "job": "Student Partner Lead",
        "imageUrl": "/images/teams/Emir.jpg",
        "links": {
            "github": "https://github.com/aemiralfath",
            "linkedin": "https://www.linkedin.com/in/aemiralfath/",
            "instagram": "https://www.instagram.com/aemiralfath/"
        }
    },
    {
        "name": "Deny Malyono",
        "job": "DevOps Engineer",
        "imageUrl": "/images/teams/Malyono.jpg",
        "links": {
            "github": "https://github.com/maximalyono"
        }
    },
    {
        "name": "Rezi Apriliansyah",
        "job": "Senior Backend Developer",
        "imageUrl": "/images/teams/Rezi.jpg",
        "links": {
            "github": "https://github.com/apranta",
            "linkedin": "https://www.linkedin.com/in/rezi-apriliansyah/",
            "instagram": "https://www.instagram.com/usernamesalah/"
        }
    },
    {
        "name": "Azhary Arliansyah",
        "job": "Senior Frontend Developer",
        "imageUrl": "/images/teams/Azhary.jpeg",
        "links": {
            "github": "https://github.com/azhry",
            "linkedin": "https://www.linkedin.com/in/azhary-arliansyah",
            "instagram": "https://instagram.com/azharyarliansyah"
        }
    },
    {
        "name": "Rizqy Adi Surya",
        "job": "UI/UX Researcher",
        "imageUrl": "/images/teams/RizkiAdi.jpeg",
        "links": {
            "github": "https://github.com/srizqiadisurya",
            "linkedin": "https://www.linkedin.com/in/rizqiadisurya/",
            "instagram": "https://www.instagram.com/rizqiadisurya/",
            "dribbble": "https://dribbble.com/rizqiadisurya"
        }
    },
    {
        "name": "Shabrina Asmarani",
        "job": "Copywriter",
        "imageUrl": "/images/teams/Shabrina.jpg",
        "links": {
            "linkedin": "https://www.linkedin.com/in/shabrinaasmarani/",
            "instagram": "https://www.instagram.com/shabrinnaaa/"
        }
    },
    {
        "name": "Riska T. Mardilah",
        "job": "Student Partner",
        "imageUrl": "/images/teams/Riska.jpg",
        "links": {
            "instagram": "https://www.instagram.com/riskaa.tm/"
        }
    },
    {
        "name": "Rizky Putra",
        "job": "Backend Developer",
        "imageUrl": "/images/teams/RizkyP.jpg",
        "links": {
            "github": "https://github.com/Hiraisin",
            "instagram": "https://www.instagram.com/rizky_pn/"
        }
    },
    {
        "name": "Misbahudin Munadi",
        "job": "Frontend Developer",
        "imageUrl": "/images/teams/Udin.jpg",
        "links": {
            "github": "https://github.com/Misbahudin04",
            "instagram": "https://www.instagram.com/save_udin/"
        }
    },
    {
        "name": "Muhammad Risky Ariyanto",
        "job": "Content Writer",
        "imageUrl": "/images/teams/RizkyA.jpg",
        "links": {
            "instagram": "https://www.instagram.com/riskygpd_/"
        }
    },
    {
        "name": "Friski Kasviko",
        "job": "Backend Developer",
        "imageUrl": "/images/teams/Friski.JPG"
    },
    {
        "name": "Taufiqulhakim",
        "job": "Frontend Developer",
        "imageUrl": "/images/teams/Taufiq.jpg",
        "links": {
            "github": "https://github.com/taufik230301",
            "instagram": "https://www.instagram.com/taufiq_hakim23/"
        }
    },
    {
        "name": "Nyayu Putri Aulia",
        "job": "Graphic Designer & Social Media",
        "imageUrl": "/images/teams/Nyayu.jpg",
        "links": {
            "instagram": "https://www.instagram.com/puthauliaa/"
        }
    },
    {
        "name": "Eko Muliyo",
        "job": "Frontend Developer",
        "imageUrl": "/images/teams/Eko.jpeg",
        "links": {
            "github": "https://github.com/ekomuliyo",
            "instagram": "https://www.instagram.com/ekomuliyo/"
        }
    },
    {
        "name": "Gerry Jeven Timoti",
        "job": "Graphic Designer & Video Editor",
        "imageUrl": "/images/teams/Gery.jpeg",
        "links": {
            "instagram": "https://www.instagram.com/gerryjeven/"
        }
    }
]